LICENSE
MANIFEST.in
README
README.md
requirements.txt
setup.py
bin/gsh
gsh/__init__.py
gsh/config.py
gsh/core.py
gsh/exceptions.py
gsh/plugin.py
gsh/util.py
gsh/version.py
gsh.egg-info/PKG-INFO
gsh.egg-info/SOURCES.txt
gsh.egg-info/dependency_links.txt
gsh.egg-info/requires.txt
gsh.egg-info/top_level.txt
gsh/plugins/README
gsh/plugins/executors/paramiko.py
gsh/plugins/executors/pexpect.py
gsh/plugins/executors/ssh.py
gsh/plugins/hooks/buffered_output_hook.py
gsh/plugins/hooks/debugger_hook.py
gsh/plugins/hooks/printer_hook.py
gsh/plugins/loaders/file_loader.py
gsh/plugins/loaders/gsh_loader.py
gsh/plugins/loaders/machine_loader.py