Metadata-Version: 1.1
Name: gsh
Version: 0.10.1
Summary: Pluggable Distributed SSH Command Executer.
Home-page: https://github.com/gmjosack/gsh
Author: Gary M. Josack
Author-email: gary@byoteki.com
License: MIT
Download-URL: https://github.com/gmjosack/gsh/archive/master.tar.gz
Platform: UNKNOWN
Classifier: Programming Language :: Python
Classifier: Topic :: Software Development
Classifier: Topic :: Software Development :: Libraries
Classifier: Topic :: Software Development :: Libraries :: Python Modules
